pycirclizely/__init__.py
pycirclizely/circos.py
pycirclizely/config.py
pycirclizely/patches.py
pycirclizely/sector.py
pycirclizely/track.py
pycirclizely/tree.py
pycirclizely/types.py
pycirclizely/impl/chord.py
pycirclizely/impl/radar.py
pycirclizely/parser/__init__.py
pycirclizely/parser/bed.py
pycirclizely/parser/genbank.py
pycirclizely/parser/gff.py
pycirclizely/parser/matrix.py
pycirclizely/parser/table.py
pycirclizely/utils/__init__.py
pycirclizely/utils/color.py
pycirclizely/utils/dataset.py
pycirclizely/utils/helper.py
pycirclizely/utils/hover_formatter.py
pycirclizely/utils/plot.py
pycirclizely/utils/example_data/images/python_logo.png
pycirclizely/utils/example_data/trees/alphabet.nwk
pycirclizely/utils/example_data/trees/large_example.nwk
pycirclizely/utils/example_data/trees/medium_example.nwk
pycirclizely/utils/example_data/trees/small_example.nwk
pycirclizely-1.0.1.dist-info/METADATA
pycirclizely-1.0.1.dist-info/WHEEL
pycirclizely-1.0.1.dist-info/licenses/LICENSE
pycirclizely-1.0.1.dist-info/RECORD
