Metadata-Version: 2.3
Name: pyCirclizely
Version: 1.0.1
Summary: Circular visualization in Python, plotly implemented
Project-URL: repository, https://github.com/Avatar-Cognition/pyCirclizely
Author-email: mirodriguezgal <miguel.rodriguezgal@gmail.com>
License: MIT
Keywords: bioinformatics,chord-diagram,circos,plotly,visualization
Classifier: Intended Audience :: Science/Research
Classifier: Programming Language :: Python :: 3
Classifier: Topic :: Scientific/Engineering :: Bio-Informatics
Requires-Python: >=3.10
Requires-Dist: biopython>=1.80
Requires-Dist: nbformat>=4.2.0
Requires-Dist: numpy>=1.21
Requires-Dist: pandas>=1.3.5
Requires-Dist: plotly==5.24.0
Requires-Dist: webcolors>=24.11
